{
  "nav": {
    "logo": "Caleb Bae",
    "links": [
      {
        "title": "Contact Me",
        "url": "https://rauftech.lemonsqueezy.com/buy/43d4f6ca-c525-497f-a77a-8148150335dc"
      }
    ]
  },

  "intro": {
    "heading": "Let’s create dance floor <span class='italic'> magic</span> for your special day",
    "icon": "/icons/intro-icon.svg"
  },

  "portrait": {
    "image": "/portrait.png"
  },

  "about": {
    "text": "I'm a software engineer passionate about full-stack development and DevOps. Experienced in Next.js and .NET, knowledgeable in Go, Python, and C#. Outside development, I enjoy tennis and post vlogs on my second Instagram account.",
    "icon": "/icons/about-icon.svg"
  },

  "contact": {
    "label": "Have some questions?",
    "heading": "Contact <span class='italic'>me</span>",
    "linkIcon": "/icons/arrow-icon.svg",
    "email": "hello@rauftech.com"
  },

  "work": {
    "projects": [
      {
        "title": "RESA",
        "url": "",
        "media": "/resa.png"
      },
      {
        "title": "Ebby",
        "url": "",
        "media": "/ebby.png"
      },
      {
        "title": "Fluently",
        "url": "",
        "media": "/fluently.png"
      },
      {
        "title": "Aqua Sentry",
        "url": "",
        "media": "/aquasentry.png"
      }
    ],
    "linkIcon": "/icons/arrow-icon-black.svg"
  },

  "socials": {
    "links": [
      {
        "title": "LinkedIn",
        "url": "https://www.LinkedIn.com/in/baecal000/"
      },
      {
        "title": "Resume",
        "url": "https://www.instagram.com/balebbae/"
      },
      {
        "title": "Github",
        "url": "https://github.com/balebbae"
      }
    ]
  }
}
